{
  "timestamp": "2023-04-12T19:51:01",
  "compiler": {
    "name": "@stencil/core",
    "version": "2.22.3",
    "typescriptVersion": "4.9.4"
  },
  "components": [
    {
      "filePath": "./src/components/mds-breadcrumb-item/mds-breadcrumb-item.tsx",
      "encapsulation": "shadow",
      "tag": "mds-breadcrumb-item",
      "readme": "# mds-breadcrumb-item\n\n\n",
      "docs": "",
      "docsTags": [],
      "usage": {},
      "props": [
        {
          "name": "selected",
          "type": "boolean | undefined",
          "mutable": true,
          "attr": "selected",
          "reflectToAttr": true,
          "docs": "Choose if the component is selected or not",
          "docsTags": [],
          "values": [
            {
              "type": "boolean"
            },
            {
              "type": "undefined"
            }
          ],
          "optional": true,
          "required": false
        }
      ],
      "methods": [],
      "events": [
        {
          "event": "mdsBreadcrumbItemSelect",
          "detail": "MdsBreadcrumbItemEventDetail",
          "bubbles": true,
          "cancelable": true,
          "composed": true,
          "docs": "Emits when the breadcrumb is active",
          "docsTags": []
        }
      ],
      "listeners": [],
      "styles": [
        {
          "name": "--mds-breadcrumb-item-arrow-depth-color",
          "annotation": "prop",
          "docs": "Sets the color of the arrow icon that separates buttons"
        },
        {
          "name": "--mds-breadcrumb-item-button-background",
          "annotation": "prop",
          "docs": "Sets the background color of the button"
        },
        {
          "name": "--mds-breadcrumb-item-button-background-hover",
          "annotation": "prop",
          "docs": "Sets the background color of the button when the mouse is over it"
        },
        {
          "name": "--mds-breadcrumb-item-button-background-selected",
          "annotation": "prop",
          "docs": "Sets the background color of the button when it's active"
        },
        {
          "name": "--mds-breadcrumb-item-button-color",
          "annotation": "prop",
          "docs": "Sets the text color of the button"
        },
        {
          "name": "--mds-breadcrumb-item-button-color-hover",
          "annotation": "prop",
          "docs": "Sets the text color of the button when the mouse is over it"
        },
        {
          "name": "--mds-breadcrumb-item-button-color-selected",
          "annotation": "prop",
          "docs": "Sets the text color of the button when it's active"
        },
        {
          "name": "--mds-breadcrumb-item-outline-blur",
          "annotation": "prop",
          "docs": "Sets the blur color when the button is blurred via keyboard"
        },
        {
          "name": "--mds-breadcrumb-item-outline-blur-offset",
          "annotation": "prop",
          "docs": "Sets the blur offset color when the button is blurred via keyboard"
        },
        {
          "name": "--mds-breadcrumb-item-outline-focus",
          "annotation": "prop",
          "docs": "Sets the focus color when the button is focused via keyboard"
        },
        {
          "name": "--mds-breadcrumb-item-outline-focus-offset",
          "annotation": "prop",
          "docs": "Sets the focus offset color when the button is focused via keyboard"
        }
      ],
      "slots": [],
      "parts": [],
      "dependents": [],
      "dependencies": [
        "mds-text"
      ],
      "dependencyGraph": {
        "mds-breadcrumb-item": [
          "mds-text"
        ]
      }
    }
  ]
}
