{
  "cosmetic": {
    "boxShadow": {
      "sharp-lg": {
        "value": "0 0 1px 1px rgb(0 0 0 / 0.06), 0 10px 15px -3px rgb(0 0 0 / 0.1), 0 4px 6px -2px rgb(0 0 0 / 0.05)"
      },
      "sharp-md": {
        "value": "0 0 1px 1px rgb(0 0 0 / 0.06), 0 4px 6px -1px rgb(0 0 0 / 0.1), 0 2px 4px -1px rgb(0 0 0 / 0.06)"
      },
      "sharp": {
        "value": "0 0 1px 1px rgb(0 0 0 / 0.06), 0 1px 3px 0 rgb(0 0 0 / 0.1)"
      },
      "sharp-sm": {
        "value": "0 0 1px 1px rgb(0 0 0 / 0.06), 0 1px 2px 0 rgb(0 0 0 / 0.05)"
      }
    }
  }
}
